senchar/__init__.py
senchar/__main__.py
senchar/database.py
senchar/display.py
senchar/ds9display.py
senchar/exceptions.py
senchar/fits.py
senchar/header.py
senchar/image.py
senchar/image_focalplane.py
senchar/image_headers.py
senchar/image_io.py
senchar/logger.py
senchar/parameters.py
senchar/plot.py
senchar/remote_logger.py
senchar/startup_example.py
senchar/utils.py
senchar/scripts/__init__.py
senchar/scripts/centroids.py
senchar/scripts/check_bits.py
senchar/scripts/display_files.py
senchar/scripts/plot_header_times.py
senchar/scripts/plot_images.py
senchar/scripts/plot_keywords.py
senchar/scripts/plot_log_temps.py
senchar/scripts/readnoise_correction.py
senchar/scripts/show_histogram.py
senchar/scripts/show_sequence_keywords.py
senchar/scripts/show_sequence_stats.py
senchar/scripts/test_gain_stability.py
senchar/scripts/threshold_image.py
senchar/tools/__init__.py
senchar/tools/basetool.py
senchar/tools/bias.py
senchar/tools/dark.py
senchar/tools/defects.py
senchar/tools/detcal.py
senchar/tools/detchar.py
senchar/tools/eper.py
senchar/tools/fe55.py
senchar/tools/gain.py
senchar/tools/gainmap.py
senchar/tools/linearity.py
senchar/tools/prnu.py
senchar/tools/ptc.py
senchar/tools/qe.py
senchar/tools/ramp.py
senchar/tools/report.css
senchar/tools/report.py
senchar/tools/superflat.py
senchar/tools/tools.py
senchar/web/__init__.py
senchar/web/fastapi_server.py
senchar/web/favicon.ico
senchar/web/index.html
senchar/web/status/__init__.py
senchar/web/status/status_card.py
senchar/web/status/status_web.py
senchar-25.0.2.dist-info/licenses/LICENSE
senchar-25.0.2.dist-info/WHEEL
senchar-25.0.2.dist-info/METADATA
senchar-25.0.2.dist-info/RECORD
