Metadata-Version: 2.4
Name: senchar
Version: 25.0.2
Summary: Scientific image sensor characterization package
Keywords: ccd,imaging,astronomy,sensors
Author: Michael Lesser
Author-email: mlesser@arizona.edu
Requires-Python: >= 3.10
License-File: LICENSE
Requires-Dist: loguru
Requires-Dist: numpy
Requires-Dist: astropy
Requires-Dist: fastapi
Requires-Dist: uvicorn
Requires-Dist: jinja2
Requires-Dist: dash
Requires-Dist: dash-bootstrap-components
Requires-Dist: dash_daq
Requires-Dist: scipy
Requires-Dist: matplotlib
Requires-Dist: pyside6
Requires-Dist: pdfkit
Requires-Dist: markdown
Requires-Dist: pypdf
Requires-Dist: mkdocstrings[python]
Project-URL: Documentation, https://senchar.readthedocs.io/
Project-URL: Repository, https://github.com/mplesser/senchar/
